webotron/__init__.py
webotron/bucket.py
webotron/cdn.py
webotron/certificate.py
webotron/domain.py
webotron/util.py
webotron/webotron.py
webotron_20-0.4.dist-info/LICENSE.txt
webotron_20-0.4.dist-info/METADATA
webotron_20-0.4.dist-info/WHEEL
webotron_20-0.4.dist-info/entry_points.txt
webotron_20-0.4.dist-info/top_level.txt
webotron_20-0.4.dist-info/RECORD
