Metadata-Version: 2.1
Name: webotron-20
Version: 0.4
Summary: Webotron 20 is a tool to deploy static website to AWS.
Home-page: https://github.com/erankitcs/automating-aws-with-python
Author: Ankit K Singh
Author-email: er.ankit.cs@gmail.com
License: MIT
Download-URL: https://github.com/erankitcs/automating-aws-with-python/archive/v0.4.tar.gz
Keywords: AWS,BOTO3,S3Website,CloudFront
Platform: UNKNOWN
Classifier: Development Status :: 3 - Alpha
Classifier: Intended Audience :: Developers
Classifier: Topic :: Software Development :: Build Tools
Classifier: License :: OSI Approved :: MIT License
Classifier: Programming Language :: Python :: 3
Classifier: Programming Language :: Python :: 3.4
Classifier: Programming Language :: Python :: 3.5
Classifier: Programming Language :: Python :: 3.6
Classifier: Programming Language :: Python :: 3.8
Requires-Dist: click
Requires-Dist: boto3
